LICENSE
MANIFEST.in
README.md
pyproject.toml
setup.cfg
setup.py
authme/__init__.py
authme/_types.py
authme/apps.py
authme/forms.py
authme/py.typed
authme/views.py
authme/conf/__init__.py
authme/conf/settings.py
authme/mixins/__init__.py
authme/mixins/access.py
authme/mixins/forms.py
authme/shortcuts/__init__.py
authme/shortcuts/one_step/__init__.py
authme/shortcuts/one_step/urls.py
authme/shortcuts/one_step/views.py
authme/systems/__init__.py
authme/systems/login/__init__.py
authme/systems/login/one_step/__init__.py
authme/systems/login/one_step/views.py
authme/systems/logout/__init__.py
authme/systems/logout/views.py
authme/systems/signup/__init__.py
authme/systems/signup/one_step/__init__.py
authme/systems/signup/one_step/views.py
authme/templates/authme/base_form.html
authme/templates/authme/base_login.html
authme/templates/authme/base_logout.html
authme/templates/authme/base_signup.html
django_authme.egg-info/PKG-INFO
django_authme.egg-info/SOURCES.txt
django_authme.egg-info/dependency_links.txt
django_authme.egg-info/requires.txt
django_authme.egg-info/top_level.txt